pyballmapper/__init__.py
pyballmapper/ballmapper.py
pyballmapper/mobm.py
pyballmapper/plotting.py
pyballmapper/tests/__init__.py
pyBallMapper-0.3.4.1.dist-info/LICENSE.md
pyBallMapper-0.3.4.1.dist-info/METADATA
pyBallMapper-0.3.4.1.dist-info/WHEEL
pyBallMapper-0.3.4.1.dist-info/top_level.txt
pyBallMapper-0.3.4.1.dist-info/RECORD
