Metadata-Version: 2.1
Name: pyBallMapper
Version: 0.3.4.1
Summary: Python implementation of the Ball Mapper algorithm.
Home-page: https://github.com/dgurnari/pyBallMapper
Author: Davide Gurnari
Author-email: davide.gurnari@gmail.com
License: LICENSE.txt
License-File: LICENSE.md
Requires-Dist: numpy
Requires-Dist: pandas
Requires-Dist: networkx
Requires-Dist: matplotlib
Requires-Dist: bokeh
Requires-Dist: numba
Requires-Dist: scikit-learn
